LICENSE
README.md
setup.py
deepmusic/__init__.py
deepmusic/conf.py
deepmusic/container.py
deepmusic/event.py
deepmusic/metrics.py
deepmusic/scale.py
deepmusic/utils.py
deepmusic.egg-info/PKG-INFO
deepmusic.egg-info/SOURCES.txt
deepmusic.egg-info/dependency_links.txt
deepmusic.egg-info/requires.txt
deepmusic.egg-info/top_level.txt