Metadata-Version: 1.2
Name: deepmusic
Version: 0.2.6
Summary: A python package to manipulate MIDI files, representing them and converting them into a proper format for feeding to machine learning models.
Home-page: https://github.com/s-omranpour/DeepMusic
Author: Soroush Omranpour
Author-email: soroush.333@gmail.com
License: MIT license
Project-URL: Bug Reports, https://github.com/s-omranpour/DeepMusic/issues
Project-URL: Source, https://github.com/s-omranpour/DeepMusic
Keywords: midi,deep learning,music
Platform: UNKNOWN
Requires-Python: >=3.7, <4
